HaplotagLR/HeterozygousSites.py
HaplotagLR/InputData.py
HaplotagLR/InputData.py~
HaplotagLR/PhasableSample.py
HaplotagLR/PhasableSample.py~
HaplotagLR/PhaseSet.py
HaplotagLR/PhaseSet.py~
HaplotagLR/PhasedRead.py
HaplotagLR/PhasedRead.py~
HaplotagLR/SimulatePhasedData.py
HaplotagLR/__init__.py
HaplotagLR/__init__.py~
HaplotagLR/__main__.py
HaplotagLR/__main__.py~
HaplotagLR/cli.py
HaplotagLR/cli.py~
HaplotagLR/urls.py
LRphase/HeterozygousSites.py
LRphase/InputData.py
LRphase/PhasableSample.py
LRphase/PhaseSet.py
LRphase/PhasedRead.py
LRphase/SimulatePhasedData.py
LRphase/__init__.py
LRphase/__main__.py
LRphase/cli.py
LRphase/urls.py
HaplotagLR-1.1.13.dist-info/LICENSE
HaplotagLR-1.1.13.dist-info/METADATA
HaplotagLR-1.1.13.dist-info/WHEEL
HaplotagLR-1.1.13.dist-info/entry_points.txt
HaplotagLR-1.1.13.dist-info/top_level.txt
HaplotagLR-1.1.13.dist-info/RECORD
