Metadata-Version: 2.1
Name: HaplotagLR
Version: 1.1.13
Summary: Phasing individual long reads using known haplotype information.
Home-page: https://github.com/Boyle-Lab/HaplotagLR.git
Author: Greg Farnum
Author-email: gregfar@umich.edu
License: MIT
Project-URL: Issue Tracker, https://github.com/Boyle-Lab/HaplotagLR/issues
Keywords: long-reads,phasing,haplotype
Platform: UNKNOWN
Classifier: License :: OSI Approved :: MIT License
Classifier: Programming Language :: Python
Classifier: Programming Language :: Python :: 3
Classifier: Programming Language :: Python :: 3.7
Classifier: Programming Language :: Python :: 3.8
Classifier: Programming Language :: Python :: 3.9
Classifier: Programming Language :: Python :: Implementation :: CPython
Classifier: Programming Language :: Python :: Implementation :: PyPy
Classifier: Intended Audience :: Science/Research
Classifier: Natural Language :: English
Classifier: Operating System :: Microsoft
Classifier: Operating System :: MacOS
Classifier: Operating System :: Unix
Classifier: Programming Language :: Python
Classifier: Topic :: Documentation
Classifier: Topic :: Scientific/Engineering :: Bio-Informatics
Classifier: Topic :: Software Development :: Libraries :: Python Modules
Classifier: Topic :: Software Development :: Version Control :: Git
Requires-Python: >=3.7
Requires-Dist: pysam (>=0.16.0.1)
Requires-Dist: biopython (>=1.78)
Requires-Dist: pyliftover (>=0.4)
Requires-Dist: powerlaw (>=1.4.6)
Requires-Dist: numpy (>=1.20.1)
Requires-Dist: requests (>=2.26.0)
Provides-Extra: mappy
Requires-Dist: mappy ; extra == 'mappy'
